{
  "$schema": "https://developer.microsoft.com/json-schemas/fabric/item/report/definition/visualContainer/2.7.0/schema.json",
  "name": "8b669a55b1871bb16024",
  "position": {
    "x": 356.15680245964643,
    "y": 428.96233666410455,
    "z": 14000,
    "height": 52.144504227517295,
    "width": 130.8531898539585,
    "tabOrder": 15000
  },
  "visual": {
    "visualType": "cardVisual",
    "query": {
      "queryState": {
        "Data": {
          "projections": [
            {
              "field": {
                "Measure": {
                  "Expression": {
                    "SourceRef": {
                      "Entity": "medidas_rfv"
                    }
                  },
                  "Property": "% Precisam de atencao"
                }
              },
              "queryRef": "medidas_rfv.% Precisam de atencao",
              "nativeQueryRef": "% Precisam de atencao"
            }
          ]
        }
      },
      "sortDefinition": {
        "sort": [
          {
            "field": {
              "Measure": {
                "Expression": {
                  "SourceRef": {
                    "Entity": "medidas_rfv"
                  }
                },
                "Property": "% Precisam de atencao"
              }
            },
            "direction": "Descending"
          }
        ],
        "isDefaultSort": true
      }
    },
    "objects": {
      "fillCustom": [
        {
          "properties": {
            "show": {
              "expr": {
                "Literal": {
                  "Value": "false"
                }
              }
            }
          }
        }
      ],
      "divider": [
        {
          "properties": {
            "show": {
              "expr": {
                "Literal": {
                  "Value": "false"
                }
              }
            }
          },
          "selector": {
            "id": "default"
          }
        }
      ],
      "outline": [
        {
          "properties": {
            "show": {
              "expr": {
                "Literal": {
                  "Value": "false"
                }
              }
            }
          },
          "selector": {
            "id": "default"
          }
        }
      ],
      "layout": [
        {
          "properties": {
            "backgroundShow": {
              "expr": {
                "Literal": {
                  "Value": "false"
                }
              }
            }
          },
          "selector": {
            "id": "default"
          }
        }
      ],
      "value": [
        {
          "properties": {
            "showBlankAs": {
              "expr": {
                "Literal": {
                  "Value": "'0%'"
                }
              }
            },
            "fontSize": {
              "expr": {
                "Literal": {
                  "Value": "10D"
                }
              }
            },
            "horizontalAlignment": {
              "expr": {
                "Literal": {
                  "Value": "'center'"
                }
              }
            }
          },
          "selector": {
            "id": "default"
          }
        }
      ],
      "label": [
        {
          "properties": {
            "show": {
              "expr": {
                "Literal": {
                  "Value": "false"
                }
              }
            }
          },
          "selector": {
            "id": "default"
          }
        }
      ]
    },
    "visualContainerObjects": {
      "background": [
        {
          "properties": {
            "show": {
              "expr": {
                "Literal": {
                  "Value": "false"
                }
              }
            },
            "color": {
              "solid": {
                "color": {
                  "expr": {
                    "ThemeDataColor": {
                      "ColorId": 3,
                      "Percent": 0
                    }
                  }
                }
              }
            },
            "transparency": {
              "expr": {
                "Literal": {
                  "Value": "100D"
                }
              }
            }
          }
        }
      ]
    },
    "drillFilterOtherVisuals": true
  }
}